WeightedEnsemble/Classification.py
WeightedEnsemble/__init__.py
WeightedEnsemble-1.0.0.dist-info/METADATA
WeightedEnsemble-1.0.0.dist-info/WHEEL
WeightedEnsemble-1.0.0.dist-info/top_level.txt
WeightedEnsemble-1.0.0.dist-info/RECORD
