Metadata-Version: 2.1
Name: WeightedEnsemble
Version: 1.0.0
Summary: will help in getting the correct classification model
Home-page: UNKNOWN
Author: Thanmay Jasti
License: UNKNOWN
Platform: UNKNOWN
Classifier: Programming Language :: Python :: 3
Classifier: License :: OSI Approved :: MIT License
Classifier: Operating System :: OS Independent
Requires-Python: >=3.6
